symdim/__init__.py
symdim-0.1.dist-info/LICENSE
symdim-0.1.dist-info/METADATA
symdim-0.1.dist-info/WHEEL
symdim-0.1.dist-info/top_level.txt
symdim-0.1.dist-info/RECORD
